deployapp
