Metadata-Version: 1.1
Name: Deployapp
Version: 0.12.1
Summary: A package to deploy sites in virtualenv, run scripts, and deploy workers with supervisor
Home-page: http://github.com/mardix/deployapp/
Author: Mardix
Author-email: mardix@github.com
License: MIT
Download-URL: http://github.com/mardix/deployapp/tarball/master
Keywords: deploy,flask,gunicorn,django,workers,deploy sites
Platform: any
Classifier: Environment :: Web Environment
Classifier: Intended Audience :: Developers
Classifier: License :: OSI Approved :: BSD License
Classifier: Operating System :: OS Independent
Classifier: Programming Language :: Python
Classifier: Programming Language :: Python :: 2
Classifier: Programming Language :: Python :: 2.6
Classifier: Programming Language :: Python :: 2.7
Classifier: Programming Language :: Python :: 3
Classifier: Programming Language :: Python :: 3.3
Classifier: Programming Language :: Python :: 3.4
Classifier: Topic :: Internet :: WWW/HTTP :: Dynamic Content
Classifier: Topic :: Software Development :: Libraries :: Python Modules
